mscookies/__init__.py
mscookies/__main__.py
mscookies/__version__.py
mscookies/cookies.py
mscookies-1.0.2.dist-info/LICENSE
mscookies-1.0.2.dist-info/METADATA
mscookies-1.0.2.dist-info/WHEEL
mscookies-1.0.2.dist-info/top_level.txt
mscookies-1.0.2.dist-info/RECORD
