Metadata-Version: 2.1
Name: mscookies
Version: 1.0.2
Summary: Loads decrypted cookiejars from Chromium based browsers running on Microsoft Windows.
Home-page: https://github.com/yportne8/MS-Cookies/
Author: CS Kim
Author-email: yportne8@gmail.com
License: MIT
Platform: UNKNOWN
Classifier: License :: OSI Approved :: MIT License
Classifier: Programming Language :: Python
Classifier: Programming Language :: Python :: 3
Classifier: Programming Language :: Python :: 3.6
Classifier: Programming Language :: Python :: Implementation :: CPython
Requires-Python: >=3.6.0
License-File: LICENSE
Requires-Dist: pycryptodome
